MANIFEST.in
README.md
setup.py
fast_sql/__init__.py
fast_sql.egg-info/PKG-INFO
fast_sql.egg-info/SOURCES.txt
fast_sql.egg-info/dependency_links.txt
fast_sql.egg-info/requires.txt
fast_sql.egg-info/top_level.txt
fast_sql/fastsql/__init__.py
fast_sql/fastsql/sql.py
fast_sql/utils/__init__.py
fast_sql/utils/common.py
fast_sql/utils/exception.py